__init__.py
ts_auth0.py
ts_auth0-0.0.14.dist-info/LICENSE
ts_auth0-0.0.14.dist-info/METADATA
ts_auth0-0.0.14.dist-info/WHEEL
ts_auth0-0.0.14.dist-info/top_level.txt
ts_auth0-0.0.14.dist-info/RECORD
