Metadata-Version: 2.1
Name: ts-auth0
Version: 0.0.14
Summary: Simple Python Auth0 login for Tradestation API v3
Author-email: Jon Richards <jrseti@gmail.com>
Project-URL: Homepage, https://github.com/jrseti/ts_auth0
Project-URL: Bug Tracker, https://github.com/jrseti/ts_auth0/issues
Classifier: Programming Language :: Python :: 3
Classifier: License :: OSI Approved :: MIT License
Classifier: Operating System :: OS Independent
Requires-Python: >=3.8
License-File: LICENSE
Requires-Dist: requests
